{
    "id": 94,
    "location": "{\"type\":\"Point\",\"coordinates\":[-1.552668530103729,53.807741261294176]}",
    "work": [
        "private",
        "close"
    ],
    "atmosphere": [
        "disciplined"
    ],
    "facilities": [
        "daylight",
        "views",
        "large_desks",
        "free_wifi",
        "computers",
        "laptops_allowed",
        "sockets",
        "signal",
        "toilets",
        "break",
        "bike_racks",
        "gender_neutral_toilets",
        "wheelchair_accessible"
    ],
    "title": "Parkinson Building - B.25",
    "description": "Perfect for focused study with access to computers. 15 seat capacity. From Parkinson Court use the stairs at the opposite end from the Café and go down to the basement. Go through the doors under the display screen and turn right. The entrance to the cluster is directly in front of you.",
    "access": "University Staff and Students",
    "space_type": "IT Cluster",
    "address": "University of Leeds, LS2 9JT",
    "building": "Parkinson building",
    "floor": "Basement",
    "restricted": true,
    "restriction": "",
    "disabled_access": true,
    "twitter_screen_name": "",
    "facebook_url": "",
    "noise": "Strictly silent",
    "tags": [],
    "opening_hours": {
        "monday": {
            "open": true,
            "from": "9:00",
            "to": "18:00"
        },
        "tuesday": {
            "open": true,
            "from": "9:00",
            "to": "18:00"
        },
        "wednesday": {
            "open": true,
            "from": "9:00",
            "to": "18:00"
        },
        "thursday": {
            "open": true,
            "from": "9:00",
            "to": "18:00"
        },
        "friday": {
            "open": true,
            "from": "9:00",
            "to": "18:00"
        },
        "saturday": {
            "open": false,
            "from": "",
            "to": ""
        },
        "sunday": {
            "open": false,
            "from": "",
            "to": ""
        }
    },
    "slug": "parkinson-building-b25",
    "published": true,
    "contacts": [],
    "links": [
        {
            "url": "https://www.leeds.ac.uk/campusmap?location=17525",
            "link_text": "View on the University campus map (map reference 60)",
            "class": "icon-uol-logo-mark"
        }
    ],
    "images": []
}